rsyslog_logger/__init__.py
rsyslog_logger/logger.py
rsyslog_logger-1.0.5.dist-info/METADATA
rsyslog_logger-1.0.5.dist-info/WHEEL
rsyslog_logger-1.0.5.dist-info/top_level.txt
rsyslog_logger-1.0.5.dist-info/RECORD
