Metadata-Version: 2.4
Name: rsyslog-logger
Version: 1.0.5
Summary: Production-ready logging with rsyslog formatting and reliable rotation
Author-email: Mahesvara <mahesvara@amhosting.de>
License-Expression: MIT
Project-URL: Homepage, https://github.com/Oratorian/rsyslog-logger
Project-URL: Repository, https://github.com/Oratorian/rsyslog-logger.git
Project-URL: Issues, https://github.com/Oratorian/rsyslog-logger/issues
Keywords: logging,rsyslog,rotation,production,syslog,monitoring
Classifier: Development Status :: 4 - Beta
Classifier: Intended Audience :: Developers
Classifier: Intended Audience :: System Administrators
Classifier: Programming Language :: Python :: 3
Classifier: Programming Language :: Python :: 3.8
Classifier: Programming Language :: Python :: 3.9
Classifier: Programming Language :: Python :: 3.10
Classifier: Programming Language :: Python :: 3.11
Classifier: Programming Language :: Python :: 3.12
Classifier: Topic :: System :: Logging
Classifier: Topic :: System :: Systems Administration
Classifier: Operating System :: OS Independent
Requires-Python: >=3.8
Provides-Extra: dev
Requires-Dist: pytest>=6.0.0; extra == "dev"
Requires-Dist: pytest-cov>=2.10.0; extra == "dev"
Requires-Dist: pytest-mock>=3.6.0; extra == "dev"
